Metadata-Version: 2.1
Name: url-to-desktop
Version: 1.0.0
Summary: Converts .url files to .desktop files
Home-page: https://github.com/xandao6/url-to-desktop
Author: Alexandre Calil Martins Fonseca
Author-email: alexandrecalilmf@gmail.com
License: MIT
Download-URL: https://pypi.org/project/url-to-desktop/
Keywords: url,link,convert,url convert,desktop conversor,url linux
Platform: UNKNOWN
Classifier: Programming Language :: Python :: 3.6
Classifier: Programming Language :: Python :: 3.7
Classifier: Programming Language :: Python :: 3 :: Only
Classifier: Operating System :: OS Independent
Requires-Python: >=3.6
